Metadata-Version: 2.1
Name: unfish
Version: 2.0.0
Summary: correct fisheye distortions in images using OpenCV
Home-page: https://github.com/elcorto/unfish
Author: Steve Schmerler
Author-email: git@elcorto.com
License: BSD 3-Clause
Keywords: camera fisheye opencv
License-File: LICENSE
